Metadata-Version: 2.1
Name: plight
Version: 0.0.1
Summary: Screen backlight adjustment
Home-page: https://github.com/ipselium/plight
Author: Cyril Desjouy
Author-email: cyril.desjouy@univ-lemans.fr
License: GPL
Platform: UNKNOWN
Classifier: Development Status :: 4 - Beta
Classifier: Programming Language :: Python :: 3
Classifier: Topic :: Software Development :: Libraries :: Python Modules
Classifier: License :: OSI Approved :: GNU General Public License v3 or later (GPLv3+)
